jaims/__init__.py
jaims/chain.py
jaims/helpers.py
jaims/jaims.py
jaims-0.0.1.dist-info/LICENSE
jaims-0.0.1.dist-info/METADATA
jaims-0.0.1.dist-info/WHEEL
jaims-0.0.1.dist-info/top_level.txt
jaims-0.0.1.dist-info/RECORD
