Metadata-Version: 2.1
Name: jaims
Version: 0.0.1
Summary: Library for jax based affine-invariant MCMC sampling
Home-page: https://github.com/utkarshgiri/jaims
Author: Utkarsh Giri
Author-email: utkarshgiri@gmail.com
License: MIT License
Project-URL: Bug Tracker, https://github.com/utkarshgiri/jaims/issues
Keywords: jax,MCMC,affine-invariant,goodman-weare,sampler
Platform: UNKNOWN
Requires-Python: >=3.7
Requires-Dist: jax (>=0.2.9)
Requires-Dist: jaxlib
Requires-Dist: numpy (>=1.20.1)
Requires-Dist: tqdm
Requires-Dist: joblib
Requires-Dist: matplotlib (>=3.4)
Requires-Dist: corner (>=2.2)
Requires-Dist: chex (>=0.0.6)
Requires-Dist: emcee
